django_loguru/__init__.py
django_loguru/configs.py
django_loguru/middleware.py
django_loguru-1.0.3.dist-info/LICENSE
django_loguru-1.0.3.dist-info/METADATA
django_loguru-1.0.3.dist-info/WHEEL
django_loguru-1.0.3.dist-info/top_level.txt
django_loguru-1.0.3.dist-info/RECORD
