Metadata-Version: 2.1
Name: django-loguru
Version: 1.0.3
Summary: A middleware to log the requests and responses using loguru.
Home-page: https://github.com/tarsil/django-loguru
Author: Tiago Silva
Author-email: tiago.arasilva@gmail.com
License: UNKNOWN
Platform: UNKNOWN
Classifier: Programming Language :: Python :: 3
Classifier: License :: OSI Approved :: MIT License
Classifier: Operating System :: OS Independent
Classifier: Environment :: Web Environment
Classifier: Framework :: Django
Classifier: Framework :: Django :: 3.1
Classifier: Framework :: Django :: 3.2
Classifier: Topic :: Software Development :: Libraries :: Python Modules
Requires-Python: >=3.7
License-File: LICENSE
Requires-Dist: django (>=3.1)
Requires-Dist: loguru
